code_pilot_cli/__init__.py
code_pilot_cli/__main__.py
code_pilot_cli/app.py
code_pilot_cli/commands/__init__.py
code_pilot_cli/commands/ai.py
code_pilot_cli/commands/chat.py
code_pilot_cli/commands/completions.py
code_pilot_cli/commands/document.py
code_pilot_cli/commands/enhance.py
code_pilot_cli/commands/review.py
code_pilot_cli/commands/scan.py
code_pilot_cli/commands/test.py
code_pilot_cli-0.2.1.dist-info/LICENSE
code_pilot_cli-0.2.1.dist-info/METADATA
code_pilot_cli-0.2.1.dist-info/WHEEL
code_pilot_cli-0.2.1.dist-info/entry_points.txt
code_pilot_cli-0.2.1.dist-info/RECORD
