Metadata-Version: 2.1
Name: code-pilot-cli
Version: 0.2.1
Summary: Your customizable codding assistant in your CLI
Home-page: https://github.com/youzarsiph/code-pilot-cli
License: MIT
Author: Yousuf Abu Shanab
Author-email: josephyousef249@gmail.com
Requires-Python: >=3.10,<4.0
Classifier: License :: OSI Approved :: MIT License
Classifier: Programming Language :: Python :: 3
Classifier: Programming Language :: Python :: 3.10
Classifier: Programming Language :: Python :: 3.11
Classifier: Programming Language :: Python :: 3.12
Classifier: Programming Language :: Python :: 3.13
Requires-Dist: huggingface-hub (>=0.25.0,<0.26.0)
Requires-Dist: typer (>=0.12.5,<0.13.0)
Project-URL: Documentation, https://github.com/youzarsiph/code-pilot-cli
Project-URL: Repository, https://github.com/youzarsiph/code-pilot-cli
